linkedin_spider/README.md
linkedin_spider/__init__.py
linkedin_spider/cli/__init__.py
linkedin_spider/cli/__main__.py
linkedin_spider/cli/main.py
linkedin_spider/core/__init__.py
linkedin_spider/core/auth.py
linkedin_spider/core/config.py
linkedin_spider/core/driver.py
linkedin_spider/core/scraper.py
linkedin_spider/mcp/__init__.py
linkedin_spider/mcp/server.py
linkedin_spider/scrapers/__init__.py
linkedin_spider/scrapers/base.py
linkedin_spider/scrapers/company.py
linkedin_spider/scrapers/connections.py
linkedin_spider/scrapers/conversations.py
linkedin_spider/scrapers/profile.py
linkedin_spider/scrapers/search.py
linkedin_spider/scrapers/search_filters.py
linkedin_spider/utils/__init__.py
linkedin_spider/utils/browser.py
linkedin_spider/utils/human_behavior.py
linkedin_spider/utils/pattern_detector.py
linkedin_spider/utils/tracking.py
linkedin_spider-0.1.2.dist-info/METADATA
linkedin_spider-0.1.2.dist-info/WHEEL
linkedin_spider-0.1.2.dist-info/entry_points.txt
linkedin_spider-0.1.2.dist-info/licenses/LICENSE
linkedin_spider-0.1.2.dist-info/RECORD
