Metadata-Version: 2.4
Name: linkedin-spider
Version: 0.1.2
Summary: A modern LinkedIn scraping library with CLI and MCP server
Project-URL: Homepage, https://github.com/vertexcover-io/linkedin-spider
Project-URL: Repository, https://github.com/vertexcover-io/linkedin-spider
Project-URL: Issues, https://github.com/vertexcover-io/linkedin-spider/issues
Project-URL: Documentation, https://github.com/vertexcover-io/linkedin-spider#readme
Author-email: Aman Kumar Singh <amankumarsingh7702@gmail.com>
License-Expression: MIT
License-File: LICENSE
Keywords: automation,cli,linkedin,mcp,scraping
Classifier: Development Status :: 4 - Beta
Classifier: Intended Audience :: Developers
Classifier: Programming Language :: Python :: 3
Classifier: Programming Language :: Python :: 3.10
Classifier: Programming Language :: Python :: 3.11
Classifier: Programming Language :: Python :: 3.12
Classifier: Programming Language :: Python :: 3.13
Classifier: Topic :: Internet
Classifier: Topic :: Internet :: WWW/HTTP :: Browsers
Classifier: Topic :: Software Development :: Libraries :: Python Modules
Requires-Python: >=3.10
Requires-Dist: psutil>=5.9.0
Requires-Dist: python-dotenv>=1.0.0
Requires-Dist: requests>=2.32.5
Requires-Dist: selenium>=4.35.0
Requires-Dist: twine>=6.2.0
Provides-Extra: all
Requires-Dist: black>=23.0.0; extra == 'all'
Requires-Dist: cyclopts>=2.0.0; extra == 'all'
Requires-Dist: fastmcp>=0.1.0; extra == 'all'
Requires-Dist: mypy>=1.0.0; extra == 'all'
Requires-Dist: pre-commit>=2.20.0; extra == 'all'
Requires-Dist: pytest-asyncio>=0.21.0; extra == 'all'
Requires-Dist: pytest>=7.2.0; extra == 'all'
Requires-Dist: ruff>=0.6.9; extra == 'all'
Provides-Extra: cli
Requires-Dist: cyclopts>=2.0.0; extra == 'cli'
Provides-Extra: dev
Requires-Dist: black>=23.0.0; extra == 'dev'
Requires-Dist: mypy>=1.0.0; extra == 'dev'
Requires-Dist: pre-commit>=2.20.0; extra == 'dev'
Requires-Dist: pytest-asyncio>=0.21.0; extra == 'dev'
Requires-Dist: pytest>=7.2.0; extra == 'dev'
Requires-Dist: ruff>=0.6.9; extra == 'dev'
Provides-Extra: mcp
Requires-Dist: cyclopts>=2.0.0; extra == 'mcp'
Requires-Dist: fastmcp>=0.1.0; extra == 'mcp'
